alwaysOn/.env
alwaysOn/__about__.py
alwaysOn/__init__.py
alwaysOn/alwaysOn.py
alwaysOn/user-agents.json
alwayson-0.0.1b2.dist-info/METADATA
alwayson-0.0.1b2.dist-info/WHEEL
alwayson-0.0.1b2.dist-info/entry_points.txt
alwayson-0.0.1b2.dist-info/licenses/LICENSE
alwayson-0.0.1b2.dist-info/RECORD
