Metadata-Version: 2.3
Name: alwaysOn
Version: 0.0.1b2
Summary: Email checker for Onoff.app.
Project-URL: Homepage, https://github.com/balestek/alwaysOn
Project-URL: Bug Tracker, https://github.com/balestek/alwaysOn/issues
Author: balestek
License:                     GNU GENERAL PUBLIC LICENSE
License-File: LICENSE
Keywords: information-gathering,investigation,onoff,open-source-intelligence,osint,osint-python,osint-tool,osint-tools,pipenv,pipx,pypi,python
Classifier: Development Status :: 4 - Beta
Classifier: Environment :: Console
Classifier: License :: OSI Approved :: GNU General Public License v3 (GPLv3)
Classifier: Natural Language :: English
Classifier: Operating System :: OS Independent
Classifier: Programming Language :: Python :: 3
Classifier: Programming Language :: Python :: 3.8
Classifier: Programming Language :: Python :: 3.9
Classifier: Programming Language :: Python :: 3.10
Classifier: Programming Language :: Python :: 3.11
Classifier: Programming Language :: Python :: 3.12
Requires-Python: >=3.8
Requires-Dist: httpx
Requires-Dist: playwright
Requires-Dist: playwright-stealth
Requires-Dist: python-dotenv
Requires-Dist: rich
